<?xml version="1.0" encoding="utf-8"?>
<DBIN2 xmlns:xsi="http://www.w3.org/2001/XMLSchema-instance" xmlns:xsd="http://www.w3.org/2001/XMLSchema" Key="1171656979" Unknown="150">
  <Entries>
    <Entry Unknown0="2117065647" Unknown1="1962341561">
      <SDL2 Key="525853235">
        <Unknown>
          <Entry>
            <Values>
              <Entry>
                <Value0>19363</Value0>
                <Value1>0</Value1>
              </Entry>
            </Values>
            <Value0>147456</Value0>
            <Value1>65536</Value1>
          </Entry>
        </Unknown>
        <Dialogs>
          <Dialog>高嶺</Dialog>
          <Dialog>好き好き大好き、ストラヴィンスキー！</Dialog>
        </Dialogs>
      </SDL2>
    </Entry>
    <Entry Unknown0="2617926349" Unknown1="1313673876">
      <SDL2 Key="525853235">
        <Unknown>
          <Entry>
            <Values>
              <Entry>
                <Value0>19364</Value0>
                <Value1>0</Value1>
              </Entry>
            </Values>
            <Value0>147456</Value0>
            <Value1>65536</Value1>
          </Entry>
        </Unknown>
        <Dialogs>
          <Dialog>高嶺</Dialog>
          <Dialog>鳴かぬなら　一緒に練習♪　ホトトギス</Dialog>
        </Dialogs>
      </SDL2>
    </Entry>
    <Entry Unknown0="2002865320" Unknown1="2758536683">
      <SDL2 Key="525853235">
        <Unknown>
          <Entry>
            <Values>
              <Entry>
                <Value0>19365</Value0>
                <Value1>0</Value1>
              </Entry>
            </Values>
            <Value0>147456</Value0>
            <Value1>65536</Value1>
          </Entry>
        </Unknown>
        <Dialogs>
          <Dialog>高嶺</Dialog>
          <Dialog>うちのお庭にいるの誰？　コニャック？　シェリー？　アップルジャック？</Dialog>
        </Dialogs>
      </SDL2>
    </Entry>
    <Entry Unknown0="2927586303" Unknown1="3343270921">
      <SDL2 Key="525853235">
        <Unknown>
          <Entry>
            <Values>
              <Entry>
                <Value0>19366</Value0>
                <Value1>0</Value1>
              </Entry>
            </Values>
            <Value0>147456</Value0>
            <Value1>65536</Value1>
          </Entry>
        </Unknown>
        <Dialogs>
          <Dialog>高嶺</Dialog>
          <Dialog>大学芋は、まだわたしたちには早いよ……。</Dialog>
        </Dialogs>
      </SDL2>
    </Entry>
    <Entry Unknown0="3428463133" Unknown1="2610782948">
      <SDL2 Key="3373819162">
        <Unknown>
          <Entry>
            <Values>
              <Entry>
                <Value0>19367</Value0>
                <Value1>0</Value1>
              </Entry>
            </Values>
            <Value0>147456</Value0>
            <Value1>65536</Value1>
          </Entry>
        </Unknown>
        <Dialogs>
          <Dialog>高嶺</Dialog>
          <Dialog>自分、めっちゃ好きやねん。</Dialog>
        </Dialogs>
      </SDL2>
    </Entry>
    <Entry Unknown0="2813402360" Unknown1="4089134395">
      <SDL2 Key="3373819162">
        <Unknown>
          <Entry>
            <Values>
              <Entry>
                <Value0>19368</Value0>
                <Value1>0</Value1>
              </Entry>
            </Values>
            <Value0>147456</Value0>
            <Value1>65536</Value1>
          </Entry>
        </Unknown>
        <Dialogs>
          <Dialog>高嶺</Dialog>
          <Dialog>エア・マナを超える新技、編み出していないとでも思って？</Dialog>
        </Dialogs>
      </SDL2>
    </Entry>
    <Entry Unknown0="516897615" Unknown1="311858265">
      <SDL2 Key="3373819162">
        <Unknown>
          <Entry>
            <Values>
              <Entry>
                <Value0>19369</Value0>
                <Value1>0</Value1>
              </Entry>
            </Values>
            <Value0>147456</Value0>
            <Value1>65536</Value1>
          </Entry>
        </Unknown>
        <Dialogs>
          <Dialog>高嶺</Dialog>
          <Dialog>一部で負け続けるよりも、二部で勝ち続けるほうがいいなんて……。</Dialog>
        </Dialogs>
      </SDL2>
    </Entry>
    <Entry Unknown0="1017823853" Unknown1="3907891764">
      <SDL2 Key="3373819162">
        <Unknown>
          <Entry>
            <Values>
              <Entry>
                <Value0>19370</Value0>
                <Value1>0</Value1>
              </Entry>
            </Values>
            <Value0>147456</Value0>
            <Value1>65536</Value1>
          </Entry>
        </Unknown>
        <Dialogs>
          <Dialog>高嶺</Dialog>
          <Dialog>料理の『さしすせそ』。砂糖、塩、酢、セロリ、そら豆。</Dialog>
        </Dialogs>
      </SDL2>
    </Entry>
    <Entry Unknown0="385985608" Unknown1="1309379979">
      <SDL2 Key="3373819162">
        <Unknown>
          <Entry>
            <Values>
              <Entry>
                <Value0>19371</Value0>
                <Value1>0</Value1>
              </Entry>
            </Values>
            <Value0>147456</Value0>
            <Value1>65536</Value1>
          </Entry>
        </Unknown>
        <Dialogs>
          <Dialog>高嶺</Dialog>
          <Dialog>前野良沢は青木昆陽の弟子！</Dialog>
        </Dialogs>
      </SDL2>
    </Entry>
    <Entry Unknown0="1310706591" Unknown1="1843848361">
      <SDL2 Key="4183333733">
        <Unknown>
          <Entry>
            <Values>
              <Entry>
                <Value0>19372</Value0>
                <Value1>0</Value1>
              </Entry>
            </Values>
            <Value0>147456</Value0>
            <Value1>65536</Value1>
          </Entry>
        </Unknown>
        <Dialogs>
          <Dialog>高嶺</Dialog>
          <Dialog>栗より美味い、四十九里！</Dialog>
        </Dialogs>
      </SDL2>
    </Entry>
    <Entry Unknown0="1828360893" Unknown1="893190788">
      <SDL2 Key="4183333733">
        <Unknown>
          <Entry>
            <Values>
              <Entry>
                <Value0>19373</Value0>
                <Value1>0</Value1>
              </Entry>
            </Values>
            <Value0>147456</Value0>
            <Value1>65536</Value1>
          </Entry>
        </Unknown>
        <Dialogs>
          <Dialog>高嶺</Dialog>
          <Dialog>夜８時過ぎてからご飯食べると太るなら、パンにすればいいじゃない。</Dialog>
        </Dialogs>
      </SDL2>
    </Entry>
    <Entry Unknown0="1196522648" Unknown1="2640043483">
      <SDL2 Key="4183333733">
        <Unknown>
          <Entry>
            <Values>
              <Entry>
                <Value0>19374</Value0>
                <Value1>0</Value1>
              </Entry>
            </Values>
            <Value0>147456</Value0>
            <Value1>65536</Value1>
          </Entry>
        </Unknown>
        <Dialogs>
          <Dialog>高嶺</Dialog>
          <Dialog>ピョンピョコビーム！</Dialog>
        </Dialogs>
      </SDL2>
    </Entry>
    <Entry Unknown0="3194985455" Unknown1="3090560249">
      <SDL2 Key="4183333733">
        <Unknown>
          <Entry>
            <Values>
              <Entry>
                <Value0>19375</Value0>
                <Value1>0</Value1>
              </Entry>
            </Values>
            <Value0>147456</Value0>
            <Value1>65536</Value1>
          </Entry>
        </Unknown>
        <Dialogs>
          <Dialog>高嶺</Dialog>
          <Dialog>ウサギってピョンとは鳴かないよね……。</Dialog>
        </Dialogs>
      </SDL2>
    </Entry>
    <Entry Unknown0="3695845901" Unknown1="2190299860">
      <SDL2 Key="4183333733">
        <Unknown>
          <Entry>
            <Values>
              <Entry>
                <Value0>19376</Value0>
                <Value1>0</Value1>
              </Entry>
            </Values>
            <Value0>147456</Value0>
            <Value1>65536</Value1>
          </Entry>
        </Unknown>
        <Dialogs>
          <Dialog>高嶺</Dialog>
          <Dialog>東方、彼氏山。とわの市出身、高嶺部屋。</Dialog>
        </Dialogs>
      </SDL2>
    </Entry>
    <Entry Unknown0="3080785128" Unknown1="3903532331">
      <SDL2 Key="4183333733">
        <Unknown>
          <Entry>
            <Values>
              <Entry>
                <Value0>19377</Value0>
                <Value1>0</Value1>
              </Entry>
            </Values>
            <Value0>147456</Value0>
            <Value1>65536</Value1>
          </Entry>
        </Unknown>
        <Dialogs>
          <Dialog>高嶺</Dialog>
          <Dialog>第一条、和をもって尊しとなす。争わないように。</Dialog>
        </Dialogs>
      </SDL2>
    </Entry>
    <Entry Unknown0="4005505855" Unknown1="193365065">
      <SDL2 Key="696828623">
        <Unknown>
          <Entry>
            <Values>
              <Entry>
                <Value0>19378</Value0>
                <Value1>0</Value1>
              </Entry>
            </Values>
            <Value0>147456</Value0>
            <Value1>65536</Value1>
          </Entry>
        </Unknown>
        <Dialogs>
          <Dialog>高嶺</Dialog>
          <Dialog>カレーパンとメロンパンどっちがすきなの!?</Dialog>
        </Dialogs>
      </SDL2>
    </Entry>
    <Entry Unknown0="211481181" Unknown1="3487408676">
      <SDL2 Key="696828623">
        <Unknown>
          <Entry>
            <Values>
              <Entry>
                <Value0>19379</Value0>
                <Value1>0</Value1>
              </Entry>
            </Values>
            <Value0>147456</Value0>
            <Value1>65536</Value1>
          </Entry>
        </Unknown>
        <Dialogs>
          <Dialog>高嶺</Dialog>
          <Dialog>わたし、ウサ美！</Dialog>
        </Dialogs>
      </SDL2>
    </Entry>
    <Entry Unknown0="3891387448" Unknown1="670793083">
      <SDL2 Key="696828623">
        <Unknown>
          <Entry>
            <Values>
              <Entry>
                <Value0>19380</Value0>
                <Value1>0</Value1>
              </Entry>
            </Values>
            <Value0>147456</Value0>
            <Value1>65536</Value1>
          </Entry>
        </Unknown>
        <Dialogs>
          <Dialog>高嶺</Dialog>
          <Dialog>これがスチームオーブンの実力？　でもアイツはこんなものじゃなかった！</Dialog>
        </Dialogs>
      </SDL2>
    </Entry>
    <Entry Unknown0="1578105743" Unknown1="1188484249">
      <SDL2 Key="696828623">
        <Unknown>
          <Entry>
            <Values>
              <Entry>
                <Value0>19381</Value0>
                <Value1>0</Value1>
              </Entry>
            </Values>
            <Value0>147456</Value0>
            <Value1>65536</Value1>
          </Entry>
        </Unknown>
        <Dialogs>
          <Dialog>高嶺</Dialog>
          <Dialog>スベスベマンジュウガニ～！</Dialog>
        </Dialogs>
      </SDL2>
    </Entry>
    <Entry Unknown0="2095743661" Unknown1="1009644148">
      <SDL2 Key="696828623">
        <Unknown>
          <Entry>
            <Values>
              <Entry>
                <Value0>19382</Value0>
                <Value1>0</Value1>
              </Entry>
            </Values>
            <Value0>147456</Value0>
            <Value1>65536</Value1>
          </Entry>
        </Unknown>
        <Dialogs>
          <Dialog>高嶺</Dialog>
          <Dialog>おいも！　カムバック！</Dialog>
        </Dialogs>
      </SDL2>
    </Entry>
    <Entry Unknown0="1463905416" Unknown1="2454441419">
      <SDL2 Key="696828623">
        <Unknown>
          <Entry>
            <Values>
              <Entry>
                <Value0>19383</Value0>
                <Value1>0</Value1>
              </Entry>
            </Values>
            <Value0>147456</Value0>
            <Value1>65536</Value1>
          </Entry>
        </Unknown>
        <Dialogs>
          <Dialog>高嶺</Dialog>
          <Dialog>別にこのリボン、狙ってなんかいないよ……。</Dialog>
        </Dialogs>
      </SDL2>
    </Entry>
    <Entry Unknown0="2388626399" Unknown1="2972067049">
      <SDL2 Key="3512288662">
        <Unknown>
          <Entry>
            <Values>
              <Entry>
                <Value0>19384</Value0>
                <Value1>0</Value1>
              </Entry>
            </Values>
            <Value0>147456</Value0>
            <Value1>65536</Value1>
          </Entry>
        </Unknown>
        <Dialogs>
          <Dialog>高嶺</Dialog>
          <Dialog>挙式はカッパドキアがいいな……。</Dialog>
        </Dialogs>
      </SDL2>
    </Entry>
    <Entry Unknown0="2889503485" Unknown1="1769816772">
      <SDL2 Key="3512288662">
        <Unknown>
          <Entry>
            <Values>
              <Entry>
                <Value0>19385</Value0>
                <Value1>0</Value1>
              </Entry>
            </Values>
            <Value0>147456</Value0>
            <Value1>65536</Value1>
          </Entry>
        </Unknown>
        <Dialogs>
          <Dialog>高嶺</Dialog>
          <Dialog>こちらは留守番電話サービスセンターではありません。</Dialog>
        </Dialogs>
      </SDL2>
    </Entry>
    <Entry Unknown0="2274442456" Unknown1="3248168219">
      <SDL2 Key="3512288662">
        <Unknown>
          <Entry>
            <Values>
              <Entry>
                <Value0>19386</Value0>
                <Value1>0</Value1>
              </Entry>
            </Values>
            <Value0>147456</Value0>
            <Value1>65536</Value1>
          </Entry>
        </Unknown>
        <Dialogs>
          <Dialog>高嶺</Dialog>
          <Dialog>スーザンざんすー！</Dialog>
        </Dialogs>
      </SDL2>
    </Entry>
    <Entry Unknown0="4272905007" Unknown1="3967185977">
      <SDL2 Key="3512288662">
        <Unknown>
          <Entry>
            <Values>
              <Entry>
                <Value0>19387</Value0>
                <Value1>0</Value1>
              </Entry>
            </Values>
            <Value0>147456</Value0>
            <Value1>65536</Value1>
          </Entry>
        </Unknown>
        <Dialogs>
          <Dialog>高嶺</Dialog>
          <Dialog>ごめん、今日は自粛……。規制解除まで、待って。</Dialog>
        </Dialogs>
      </SDL2>
    </Entry>
    <Entry Unknown0="478863949" Unknown1="3603796500">
      <SDL2 Key="3512288662">
        <Unknown>
          <Entry>
            <Values>
              <Entry>
                <Value0>19388</Value0>
                <Value1>0</Value1>
              </Entry>
            </Values>
            <Value0>147456</Value0>
            <Value1>65536</Value1>
          </Entry>
        </Unknown>
        <Dialogs>
          <Dialog>高嶺</Dialog>
          <Dialog>セクシーな頭蓋骨ね？</Dialog>
        </Dialogs>
      </SDL2>
    </Entry>
    <Entry Unknown0="4158770216" Unknown1="1022061931">
      <SDL2 Key="3512288662">
        <Unknown>
          <Entry>
            <Values>
              <Entry>
                <Value0>19389</Value0>
                <Value1>0</Value1>
              </Entry>
            </Values>
            <Value0>147456</Value0>
            <Value1>65536</Value1>
          </Entry>
        </Unknown>
        <Dialogs>
          <Dialog>高嶺</Dialog>
          <Dialog>水族館、楽しいね！　ほら、次は蘇我入鹿見にいこ♪</Dialog>
        </Dialogs>
      </SDL2>
    </Entry>
    <Entry Unknown0="788523903" Unknown1="1606861961">
      <SDL2 Key="327777266">
        <Unknown>
          <Entry>
            <Values>
              <Entry>
                <Value0>19390</Value0>
                <Value1>0</Value1>
              </Entry>
            </Values>
            <Value0>147456</Value0>
            <Value1>65536</Value1>
          </Entry>
        </Unknown>
        <Dialogs>
          <Dialog>高嶺</Dialog>
          <Dialog>小野焼き妹子……おいしい！</Dialog>
        </Dialogs>
      </SDL2>
    </Entry>
    <Entry Unknown0="1289400989" Unknown1="52290148">
      <SDL2 Key="327777266">
        <Unknown>
          <Entry>
            <Values>
              <Entry>
                <Value0>19391</Value0>
                <Value1>0</Value1>
              </Entry>
            </Values>
            <Value0>147456</Value0>
            <Value1>65536</Value1>
          </Entry>
        </Unknown>
        <Dialogs>
          <Dialog>高嶺</Dialog>
          <Dialog>パパラッチ、パパアンラッチ。</Dialog>
        </Dialogs>
      </SDL2>
    </Entry>
    <Entry Unknown0="657562744" Unknown1="1799077307">
      <SDL2 Key="327777266">
        <Unknown>
          <Entry>
            <Values>
              <Entry>
                <Value0>19392</Value0>
                <Value1>0</Value1>
              </Entry>
            </Values>
            <Value0>147456</Value0>
            <Value1>65536</Value1>
          </Entry>
        </Unknown>
        <Dialogs>
          <Dialog>高嶺</Dialog>
          <Dialog>君の瞳にナマステ。</Dialog>
        </Dialogs>
      </SDL2>
    </Entry>
    <Entry Unknown0="2656025551" Unknown1="2316702937">
      <SDL2 Key="327777266">
        <Unknown>
          <Entry>
            <Values>
              <Entry>
                <Value0>19393</Value0>
                <Value1>0</Value1>
              </Entry>
            </Values>
            <Value0>147456</Value0>
            <Value1>65536</Value1>
          </Entry>
        </Unknown>
        <Dialogs>
          <Dialog>高嶺</Dialog>
          <Dialog>高嶺愛花、歌います！</Dialog>
        </Dialogs>
      </SDL2>
    </Entry>
    <Entry Unknown0="3156886253" Unknown1="1886204596">
      <SDL2 Key="327777266">
        <Unknown>
          <Entry>
            <Values>
              <Entry>
                <Value0>19394</Value0>
                <Value1>0</Value1>
              </Entry>
            </Values>
            <Value0>147456</Value0>
            <Value1>65536</Value1>
          </Entry>
        </Unknown>
        <Dialogs>
          <Dialog>高嶺</Dialog>
          <Dialog>クラスの半分が双子……？</Dialog>
        </Dialogs>
      </SDL2>
    </Entry>
    <Entry Unknown0="2541825224" Unknown1="3867872523">
      <SDL2 Key="327777266">
        <Unknown>
          <Entry>
            <Values>
              <Entry>
                <Value0>19395</Value0>
                <Value1>0</Value1>
              </Entry>
            </Values>
            <Value0>147456</Value0>
            <Value1>65536</Value1>
          </Entry>
        </Unknown>
        <Dialogs>
          <Dialog>高嶺</Dialog>
          <Dialog>プラチナ生徒手帳を手にいれたよ。やったね！</Dialog>
        </Dialogs>
      </SDL2>
    </Entry>
    <Entry Unknown0="3466545951" Unknown1="3311821865">
      <SDL2 Key="3378245320">
        <Unknown>
          <Entry>
            <Values>
              <Entry>
                <Value0>19396</Value0>
                <Value1>0</Value1>
              </Entry>
            </Values>
            <Value0>147456</Value0>
            <Value1>65536</Value1>
          </Entry>
        </Unknown>
        <Dialogs>
          <Dialog>高嶺</Dialog>
          <Dialog>好きなの……わたし、ホッケが好きなの！</Dialog>
        </Dialogs>
      </SDL2>
    </Entry>
    <Entry Unknown0="3967423037" Unknown1="2646442500">
      <SDL2 Key="3378245320">
        <Unknown>
          <Entry>
            <Values>
              <Entry>
                <Value0>19397</Value0>
                <Value1>0</Value1>
              </Entry>
            </Values>
            <Value0>147456</Value0>
            <Value1>65536</Value1>
          </Entry>
        </Unknown>
        <Dialogs>
          <Dialog>高嶺</Dialog>
          <Dialog>川に洗濯に行ってきまーす！　どんぶらこどんぶらこ。</Dialog>
        </Dialogs>
      </SDL2>
    </Entry>
    <Entry Unknown0="3352427544" Unknown1="903568731">
      <SDL2 Key="3378245320">
        <Unknown>
          <Entry>
            <Values>
              <Entry>
                <Value0>19398</Value0>
                <Value1>0</Value1>
              </Entry>
            </Values>
            <Value0>147456</Value0>
            <Value1>65536</Value1>
          </Entry>
        </Unknown>
        <Dialogs>
          <Dialog>高嶺</Dialog>
          <Dialog>いいお庭ですね。とても詩的。そう、ポエミー。</Dialog>
        </Dialogs>
      </SDL2>
    </Entry>
    <Entry Unknown0="1055857519" Unknown1="280409209">
      <SDL2 Key="3378245320">
        <Unknown>
          <Entry>
            <Values>
              <Entry>
                <Value0>19399</Value0>
                <Value1>0</Value1>
              </Entry>
            </Values>
            <Value0>147456</Value0>
            <Value1>65536</Value1>
          </Entry>
        </Unknown>
        <Dialogs>
          <Dialog>高嶺</Dialog>
          <Dialog>もっとおなかに力を入れて！　歯を食いしばって！　優しくわたしの手を握って？</Dialog>
        </Dialogs>
      </SDL2>
    </Entry>
    <Entry Unknown0="1556783757" Unknown1="705548884">
      <SDL2 Key="3378245320">
        <Unknown>
          <Entry>
            <Values>
              <Entry>
                <Value0>19400</Value0>
                <Value1>0</Value1>
              </Entry>
            </Values>
            <Value0>147456</Value0>
            <Value1>65536</Value1>
          </Entry>
        </Unknown>
        <Dialogs>
          <Dialog>高嶺</Dialog>
          <Dialog>冷蔵庫の中は豆腐とチョコと人参……何作ろうかな。</Dialog>
        </Dialogs>
      </SDL2>
    </Entry>
    <Entry Unknown0="924945512" Unknown1="1076604331">
      <SDL2 Key="3378245320">
        <Unknown>
          <Entry>
            <Values>
              <Entry>
                <Value0>19401</Value0>
                <Value1>0</Value1>
              </Entry>
            </Values>
            <Value0>147456</Value0>
            <Value1>65536</Value1>
          </Entry>
        </Unknown>
        <Dialogs>
          <Dialog>高嶺</Dialog>
          <Dialog>確保ー！　担保ー！　損保ー！　安保ー！</Dialog>
        </Dialogs>
      </SDL2>
    </Entry>
    <Entry Unknown0="1849666495" Unknown1="2735080649">
      <SDL2 Key="3951765027">
        <Unknown>
          <Entry>
            <Values>
              <Entry>
                <Value0>19402</Value0>
                <Value1>0</Value1>
              </Entry>
            </Values>
            <Value0>147456</Value0>
            <Value1>65536</Value1>
          </Entry>
        </Unknown>
        <Dialogs>
          <Dialog>高嶺</Dialog>
          <Dialog>ご注文を繰り返します。焼き芋ステーキ、焼き芋サラダ、焼き芋パフェ、でよろしいですか？</Dialog>
        </Dialogs>
      </SDL2>
    </Entry>
    <Entry Unknown0="2350543581" Unknown1="2002592420">
      <SDL2 Key="3951765027">
        <Unknown>
          <Entry>
            <Values>
              <Entry>
                <Value0>19403</Value0>
                <Value1>0</Value1>
              </Entry>
            </Values>
            <Value0>147456</Value0>
            <Value1>65536</Value1>
          </Entry>
        </Unknown>
        <Dialogs>
          <Dialog>高嶺</Dialog>
          <Dialog>お野菜をもっと食べなさい！　肉１に対して、野菜１０！</Dialog>
        </Dialogs>
      </SDL2>
    </Entry>
    <Entry Unknown0="1735482552" Unknown1="2675703291">
      <SDL2 Key="3951765027">
        <Unknown>
          <Entry>
            <Values>
              <Entry>
                <Value0>19404</Value0>
                <Value1>0</Value1>
              </Entry>
            </Values>
            <Value0>147456</Value0>
            <Value1>65536</Value1>
          </Entry>
        </Unknown>
        <Dialogs>
          <Dialog>高嶺</Dialog>
          <Dialog>それもう焦げてる！　食べちゃダメ！</Dialog>
        </Dialogs>
      </SDL2>
    </Entry>
    <Entry Unknown0="3733945103" Unknown1="4267070489">
      <SDL2 Key="3951765027">
        <Unknown>
          <Entry>
            <Values>
              <Entry>
                <Value0>19405</Value0>
                <Value1>0</Value1>
              </Entry>
            </Values>
            <Value0>147456</Value0>
            <Value1>65536</Value1>
          </Entry>
        </Unknown>
        <Dialogs>
          <Dialog>高嶺</Dialog>
          <Dialog>たくさんのアンコールありがとう！　でもアンコールはハタチになってからじゃないと。</Dialog>
        </Dialogs>
      </SDL2>
    </Entry>
    <Entry Unknown0="4234805805" Unknown1="2225959668">
      <SDL2 Key="3951765027">
        <Unknown>
          <Entry>
            <Values>
              <Entry>
                <Value0>19406</Value0>
                <Value1>0</Value1>
              </Entry>
            </Values>
            <Value0>147456</Value0>
            <Value1>65536</Value1>
          </Entry>
        </Unknown>
        <Dialogs>
          <Dialog>高嶺</Dialog>
          <Dialog>廊下は走らないで、ほふく前進。</Dialog>
        </Dialogs>
      </SDL2>
    </Entry>
    <Entry Unknown0="3619810312" Unknown1="717966667">
      <SDL2 Key="3951765027">
        <Unknown>
          <Entry>
            <Values>
              <Entry>
                <Value0>19407</Value0>
                <Value1>0</Value1>
              </Entry>
            </Values>
            <Value0>147456</Value0>
            <Value1>65536</Value1>
          </Entry>
        </Unknown>
        <Dialogs>
          <Dialog>高嶺</Dialog>
          <Dialog>挨拶は大きな声で、人の悪口はもっと大きな声で。</Dialog>
        </Dialogs>
      </SDL2>
    </Entry>
    <Entry Unknown0="249498463" Unknown1="161916009">
      <SDL2 Key="3951765027">
        <Unknown>
          <Entry>
            <Values>
              <Entry>
                <Value0>19408</Value0>
                <Value1>0</Value1>
              </Entry>
            </Values>
            <Value0>147456</Value0>
            <Value1>65536</Value1>
          </Entry>
        </Unknown>
        <Dialogs>
          <Dialog>高嶺</Dialog>
          <Dialog>食べるな危険。</Dialog>
        </Dialogs>
      </SDL2>
    </Entry>
    <Entry Unknown0="750441085" Unknown1="3523068484">
      <SDL2 Key="733629582">
        <Unknown>
          <Entry>
            <Values>
              <Entry>
                <Value0>19409</Value0>
                <Value1>0</Value1>
              </Entry>
            </Values>
            <Value0>147456</Value0>
            <Value1>65536</Value1>
          </Entry>
        </Unknown>
        <Dialogs>
          <Dialog>高嶺</Dialog>
          <Dialog>何これ、しゃもじだらけ……。</Dialog>
        </Dialogs>
      </SDL2>
    </Entry>
    <Entry Unknown0="118602840" Unknown1="2031852955">
      <SDL2 Key="733629582">
        <Unknown>
          <Entry>
            <Values>
              <Entry>
                <Value0>19410</Value0>
                <Value1>0</Value1>
              </Entry>
            </Values>
            <Value0>147456</Value0>
            <Value1>65536</Value1>
          </Entry>
        </Unknown>
        <Dialogs>
          <Dialog>高嶺</Dialog>
          <Dialog>今日の罰ゲームは、家まで蟹歩き。</Dialog>
        </Dialogs>
      </SDL2>
    </Entry>
    <Entry Unknown0="2117065647" Unknown1="1157035193">
      <SDL2 Key="733629582">
        <Unknown>
          <Entry>
            <Values>
              <Entry>
                <Value0>19411</Value0>
                <Value1>0</Value1>
              </Entry>
            </Values>
            <Value0>147456</Value0>
            <Value1>65536</Value1>
          </Entry>
        </Unknown>
        <Dialogs>
          <Dialog>高嶺</Dialog>
          <Dialog>それって三角食べよね？</Dialog>
        </Dialogs>
      </SDL2>
    </Entry>
    <Entry Unknown0="2617926349" Unknown1="2118980244">
      <SDL2 Key="733629582">
        <Unknown>
          <Entry>
            <Values>
              <Entry>
                <Value0>19412</Value0>
                <Value1>0</Value1>
              </Entry>
            </Values>
            <Value0>147456</Value0>
            <Value1>65536</Value1>
          </Entry>
        </Unknown>
        <Dialogs>
          <Dialog>高嶺</Dialog>
          <Dialog>いくらサーターアンダギーでも許せない。</Dialog>
        </Dialogs>
      </SDL2>
    </Entry>
    <Entry Unknown0="2002865320" Unknown1="2490101227">
      <SDL2 Key="733629582">
        <Unknown>
          <Entry>
            <Values>
              <Entry>
                <Value0>19413</Value0>
                <Value1>0</Value1>
              </Entry>
            </Values>
            <Value0>147456</Value0>
            <Value1>65536</Value1>
          </Entry>
        </Unknown>
        <Dialogs>
          <Dialog>高嶺</Dialog>
          <Dialog>いかめししかありえないね？</Dialog>
        </Dialogs>
      </SDL2>
    </Entry>
    <Entry Unknown0="2927586303" Unknown1="4148577289">
      <SDL2 Key="733629582">
        <Unknown>
          <Entry>
            <Values>
              <Entry>
                <Value0>19414</Value0>
                <Value1>0</Value1>
              </Entry>
            </Values>
            <Value0>147456</Value0>
            <Value1>65536</Value1>
          </Entry>
        </Unknown>
        <Dialogs>
          <Dialog>高嶺</Dialog>
          <Dialog>ホップステップ別府♪</Dialog>
        </Dialogs>
      </SDL2>
    </Entry>
    <Entry Unknown0="3428463133" Unknown1="2879218404">
      <SDL2 Key="3280785237">
        <Unknown>
          <Entry>
            <Values>
              <Entry>
                <Value0>19415</Value0>
                <Value1>0</Value1>
              </Entry>
            </Values>
            <Value0>147456</Value0>
            <Value1>65536</Value1>
          </Entry>
        </Unknown>
        <Dialogs>
          <Dialog>高嶺</Dialog>
          <Dialog>へーんしん！　あれ、できない。違うの、もう一回！</Dialog>
        </Dialogs>
      </SDL2>
    </Entry>
    <Entry Unknown0="2813402360" Unknown1="3283828027">
      <SDL2 Key="3280785237">
        <Unknown>
          <Entry>
            <Values>
              <Entry>
                <Value0>19416</Value0>
                <Value1>0</Value1>
              </Entry>
            </Values>
            <Value0>147456</Value0>
            <Value1>65536</Value1>
          </Entry>
        </Unknown>
        <Dialogs>
          <Dialog>高嶺</Dialog>
          <Dialog>「たいく」じゃなくて、「たいいく」！</Dialog>
        </Dialogs>
      </SDL2>
    </Entry>
    <Entry Unknown0="516897615" Unknown1="580293721">
      <SDL2 Key="3280785237">
        <Unknown>
          <Entry>
            <Values>
              <Entry>
                <Value0>19417</Value0>
                <Value1>0</Value1>
              </Entry>
            </Values>
            <Value0>147456</Value0>
            <Value1>65536</Value1>
          </Entry>
        </Unknown>
        <Dialogs>
          <Dialog>高嶺</Dialog>
          <Dialog>今日のおやつは、洋風落雁。</Dialog>
        </Dialogs>
      </SDL2>
    </Entry>
    <Entry Unknown0="1017823853" Unknown1="3639456308">
      <SDL2 Key="3280785237">
        <Unknown>
          <Entry>
            <Values>
              <Entry>
                <Value0>19418</Value0>
                <Value1>0</Value1>
              </Entry>
            </Values>
            <Value0>147456</Value0>
            <Value1>65536</Value1>
          </Entry>
        </Unknown>
        <Dialogs>
          <Dialog>高嶺</Dialog>
          <Dialog>一週間の始まりって、日曜日と月曜日のどっちが正しいんだろう？</Dialog>
        </Dialogs>
      </SDL2>
    </Entry>
    <Entry Unknown0="385985608" Unknown1="2114686347">
      <SDL2 Key="3280785237">
        <Unknown>
          <Entry>
            <Values>
              <Entry>
                <Value0>19419</Value0>
                <Value1>0</Value1>
              </Entry>
            </Values>
            <Value0>147456</Value0>
            <Value1>65536</Value1>
          </Entry>
        </Unknown>
        <Dialogs>
          <Dialog>高嶺</Dialog>
          <Dialog>お待たせしました、カレーとシチューとハヤシライスの特製ブレンドです♪</Dialog>
        </Dialogs>
      </SDL2>
    </Entry>
    <Entry Unknown0="1310706591" Unknown1="1575412905">
      <SDL2 Key="3280785237">
        <Unknown>
          <Entry>
            <Values>
              <Entry>
                <Value0>19420</Value0>
                <Value1>0</Value1>
              </Entry>
            </Values>
            <Value0>147456</Value0>
            <Value1>65536</Value1>
          </Entry>
        </Unknown>
        <Dialogs>
          <Dialog>高嶺</Dialog>
          <Dialog>電動歯ブラシ用の歯磨き粉、ください。</Dialog>
        </Dialogs>
      </SDL2>
    </Entry>
    <Entry Unknown0="1828360893" Unknown1="87884420">
      <SDL2 Key="3280785237">
        <Unknown>
          <Entry>
            <Values>
              <Entry>
                <Value0>19421</Value0>
                <Value1>0</Value1>
              </Entry>
            </Values>
            <Value0>147456</Value0>
            <Value1>65536</Value1>
          </Entry>
        </Unknown>
        <Dialogs>
          <Dialog>高嶺</Dialog>
          <Dialog>このカードはお客様の都合により利用停止になっております。</Dialog>
        </Dialogs>
      </SDL2>
    </Entry>
    <Entry Unknown0="1196522648" Unknown1="2908478939">
      <SDL2 Key="4122797759">
        <Unknown>
          <Entry>
            <Values>
              <Entry>
                <Value0>19422</Value0>
                <Value1>0</Value1>
              </Entry>
            </Values>
            <Value0>147456</Value0>
            <Value1>65536</Value1>
          </Entry>
        </Unknown>
        <Dialogs>
          <Dialog>高嶺</Dialog>
          <Dialog>約束の時間には、電波時計なみに正確ね。</Dialog>
        </Dialogs>
      </SDL2>
    </Entry>
    <Entry Unknown0="3194985455" Unknown1="2285253881">
      <SDL2 Key="4122797759">
        <Unknown>
          <Entry>
            <Values>
              <Entry>
                <Value0>19423</Value0>
                <Value1>0</Value1>
              </Entry>
            </Values>
            <Value0>147456</Value0>
            <Value1>65536</Value1>
          </Entry>
        </Unknown>
        <Dialogs>
          <Dialog>高嶺</Dialog>
          <Dialog>ハミガキ粉は、歯ブラシの三分の一までにして！</Dialog>
        </Dialogs>
      </SDL2>
    </Entry>
    <Entry Unknown0="3695845901" Unknown1="2995606228">
      <SDL2 Key="4122797759">
        <Unknown>
          <Entry>
            <Values>
              <Entry>
                <Value0>19424</Value0>
                <Value1>0</Value1>
              </Entry>
            </Values>
            <Value0>147456</Value0>
            <Value1>65536</Value1>
          </Entry>
        </Unknown>
        <Dialogs>
          <Dialog>高嶺</Dialog>
          <Dialog>ぬかにくぎゅ！</Dialog>
        </Dialogs>
      </SDL2>
    </Entry>
    <Entry Unknown0="3080785128" Unknown1="3635096875">
      <SDL2 Key="4122797759">
        <Unknown>
          <Entry>
            <Values>
              <Entry>
                <Value0>19425</Value0>
                <Value1>0</Value1>
              </Entry>
            </Values>
            <Value0>147456</Value0>
            <Value1>65536</Value1>
          </Entry>
        </Unknown>
        <Dialogs>
          <Dialog>高嶺</Dialog>
          <Dialog>８０℃のお湯で、３分間蒸らして？</Dialog>
        </Dialogs>
      </SDL2>
    </Entry>
    <Entry Unknown0="4005505855" Unknown1="998671433">
      <SDL2 Key="4122797759">
        <Unknown>
          <Entry>
            <Values>
              <Entry>
                <Value0>19426</Value0>
                <Value1>0</Value1>
              </Entry>
            </Values>
            <Value0>147456</Value0>
            <Value1>65536</Value1>
          </Entry>
        </Unknown>
        <Dialogs>
          <Dialog>高嶺</Dialog>
          <Dialog>看板を出してないお店に入るのが夢なの。</Dialog>
        </Dialogs>
      </SDL2>
    </Entry>
    <Entry Unknown0="211481181" Unknown1="2682102308">
      <SDL2 Key="4122797759">
        <Unknown>
          <Entry>
            <Values>
              <Entry>
                <Value0>19427</Value0>
                <Value1>0</Value1>
              </Entry>
            </Values>
            <Value0>147456</Value0>
            <Value1>65536</Value1>
          </Entry>
        </Unknown>
        <Dialogs>
          <Dialog>高嶺</Dialog>
          <Dialog>たくあん、柴漬け、奈良漬け、福神漬け。</Dialog>
        </Dialogs>
      </SDL2>
    </Entry>
    <Entry Unknown0="3891387448" Unknown1="2012970363">
      <SDL2 Key="3146611078">
        <Unknown>
          <Entry>
            <Values>
              <Entry>
                <Value0>19428</Value0>
                <Value1>0</Value1>
              </Entry>
            </Values>
            <Value0>147456</Value0>
            <Value1>65536</Value1>
          </Entry>
        </Unknown>
        <Dialogs>
          <Dialog>高嶺</Dialog>
          <Dialog>魚ヘンに弱いはイワシ。じゃあ、魚ヘンに強いは？</Dialog>
        </Dialogs>
      </SDL2>
    </Entry>
    <Entry Unknown0="1578105743" Unknown1="383177881">
      <SDL2 Key="3146611078">
        <Unknown>
          <Entry>
            <Values>
              <Entry>
                <Value0>19429</Value0>
                <Value1>0</Value1>
              </Entry>
            </Values>
            <Value0>147456</Value0>
            <Value1>65536</Value1>
          </Entry>
        </Unknown>
        <Dialogs>
          <Dialog>高嶺</Dialog>
          <Dialog>雪が降ってきた……。シロップどこだっけ？</Dialog>
        </Dialogs>
      </SDL2>
    </Entry>
    <Entry Unknown0="2095743661" Unknown1="1814950516">
      <SDL2 Key="3146611078">
        <Unknown>
          <Entry>
            <Values>
              <Entry>
                <Value0>19430</Value0>
                <Value1>0</Value1>
              </Entry>
            </Values>
            <Value0>147456</Value0>
            <Value1>65536</Value1>
          </Entry>
        </Unknown>
        <Dialogs>
          <Dialog>高嶺</Dialog>
          <Dialog>春はあけぼの、夏は……コニシキ！</Dialog>
        </Dialogs>
      </SDL2>
    </Entry>
    <Entry Unknown0="1463905416" Unknown1="3259747787">
      <SDL2 Key="3146611078">
        <Unknown>
          <Entry>
            <Values>
              <Entry>
                <Value0>19431</Value0>
                <Value1>0</Value1>
              </Entry>
            </Values>
            <Value0>147456</Value0>
            <Value1>65536</Value1>
          </Entry>
        </Unknown>
        <Dialogs>
          <Dialog>高嶺</Dialog>
          <Dialog>そんな実装じゃ拡張に耐えられないよ……。</Dialog>
        </Dialogs>
      </SDL2>
    </Entry>
    <Entry Unknown0="2388626399" Unknown1="3777373417">
      <SDL2 Key="3146611078">
        <Unknown>
          <Entry>
            <Values>
              <Entry>
                <Value0>19432</Value0>
                <Value1>0</Value1>
              </Entry>
            </Values>
            <Value0>147456</Value0>
            <Value1>65536</Value1>
          </Entry>
        </Unknown>
        <Dialogs>
          <Dialog>高嶺</Dialog>
          <Dialog>不適切な発言がありましたことをお詫びいたします。</Dialog>
        </Dialogs>
      </SDL2>
    </Entry>
    <Entry Unknown0="2889503485" Unknown1="964510404">
      <SDL2 Key="3146611078">
        <Unknown>
          <Entry>
            <Values>
              <Entry>
                <Value0>19433</Value0>
                <Value1>0</Value1>
              </Entry>
            </Values>
            <Value0>147456</Value0>
            <Value1>65536</Value1>
          </Entry>
        </Unknown>
        <Dialogs>
          <Dialog>高嶺</Dialog>
          <Dialog>ふぅん、メガてりやきうどんバーガーがあるのにね。</Dialog>
        </Dialogs>
      </SDL2>
    </Entry>
    <Entry Unknown0="2274442456" Unknown1="2442861851">
      <SDL2 Key="3146611078">
        <Unknown>
          <Entry>
            <Values>
              <Entry>
                <Value0>19434</Value0>
                <Value1>0</Value1>
              </Entry>
            </Values>
            <Value0>147456</Value0>
            <Value1>65536</Value1>
          </Entry>
        </Unknown>
        <Dialogs>
          <Dialog>高嶺</Dialog>
          <Dialog>わたし、アイドルデビューします！</Dialog>
        </Dialogs>
      </SDL2>
    </Entry>
    <Entry Unknown0="4272905007" Unknown1="3161879609">
      <SDL2 Key="3720191970">
        <Unknown>
          <Entry>
            <Values>
              <Entry>
                <Value0>19435</Value0>
                <Value1>0</Value1>
              </Entry>
            </Values>
            <Value0>147456</Value0>
            <Value1>65536</Value1>
          </Entry>
        </Unknown>
        <Dialogs>
          <Dialog>高嶺</Dialog>
          <Dialog>それは十六進数でってこと？</Dialog>
        </Dialogs>
      </SDL2>
    </Entry>
    <Entry Unknown0="478863949" Unknown1="2261619220">
      <SDL2 Key="3720191970">
        <Unknown>
          <Entry>
            <Values>
              <Entry>
                <Value0>19436</Value0>
                <Value1>0</Value1>
              </Entry>
            </Values>
            <Value0>147456</Value0>
            <Value1>65536</Value1>
          </Entry>
        </Unknown>
        <Dialogs>
          <Dialog>高嶺</Dialog>
          <Dialog>お金をドブに捨てる気なの？</Dialog>
        </Dialogs>
      </SDL2>
    </Entry>
    <Entry Unknown0="4158770216" Unknown1="1827368299">
      <SDL2 Key="3720191970">
        <Unknown>
          <Entry>
            <Values>
              <Entry>
                <Value0>19437</Value0>
                <Value1>0</Value1>
              </Entry>
            </Values>
            <Value0>147456</Value0>
            <Value1>65536</Value1>
          </Entry>
        </Unknown>
        <Dialogs>
          <Dialog>高嶺</Dialog>
          <Dialog>ふぅ、なんとか致命傷だけで済んだよ。</Dialog>
        </Dialogs>
      </SDL2>
    </Entry>
    <Entry Unknown0="788523903" Unknown1="264684681">
      <SDL2 Key="3720191970">
        <Unknown>
          <Entry>
            <Values>
              <Entry>
                <Value0>19438</Value0>
                <Value1>0</Value1>
              </Entry>
            </Values>
            <Value0>147456</Value0>
            <Value1>65536</Value1>
          </Entry>
        </Unknown>
        <Dialogs>
          <Dialog>高嶺</Dialog>
          <Dialog>あなたのフィールを感じる。</Dialog>
        </Dialogs>
      </SDL2>
    </Entry>
    <Entry Unknown0="1289400989" Unknown1="1394467428">
      <SDL2 Key="3720191970">
        <Unknown>
          <Entry>
            <Values>
              <Entry>
                <Value0>19439</Value0>
                <Value1>0</Value1>
              </Entry>
            </Values>
            <Value0>147456</Value0>
            <Value1>65536</Value1>
          </Entry>
        </Unknown>
        <Dialogs>
          <Dialog>高嶺</Dialog>
          <Dialog>カチューシャを２個付けるのって変かな？</Dialog>
        </Dialogs>
      </SDL2>
    </Entry>
    <Entry Unknown0="657562744" Unknown1="993770939">
      <SDL2 Key="502122316">
        <Unknown>
          <Entry>
            <Values>
              <Entry>
                <Value0>19440</Value0>
                <Value1>0</Value1>
              </Entry>
            </Values>
            <Value0>147456</Value0>
            <Value1>65536</Value1>
          </Entry>
        </Unknown>
        <Dialogs>
          <Dialog>高嶺</Dialog>
          <Dialog>富士山麓にオウムっているのかな？</Dialog>
        </Dialogs>
      </SDL2>
    </Entry>
    <Entry Unknown0="2656025551" Unknown1="3658880217">
      <SDL2 Key="502122316">
        <Unknown>
          <Entry>
            <Values>
              <Entry>
                <Value0>19441</Value0>
                <Value1>0</Value1>
              </Entry>
            </Values>
            <Value0>147456</Value0>
            <Value1>65536</Value1>
          </Entry>
        </Unknown>
        <Dialogs>
          <Dialog>高嶺</Dialog>
          <Dialog>カレー南蛮とカレーうどんってどこが違うの？</Dialog>
        </Dialogs>
      </SDL2>
    </Entry>
    <Entry Unknown0="3156886253" Unknown1="544027316">
      <SDL2 Key="502122316">
        <Unknown>
          <Entry>
            <Values>
              <Entry>
                <Value0>19442</Value0>
                <Value1>0</Value1>
              </Entry>
            </Values>
            <Value0>147456</Value0>
            <Value1>65536</Value1>
          </Entry>
        </Unknown>
        <Dialogs>
          <Dialog>高嶺</Dialog>
          <Dialog>足の人差し指触ってると、中指みたいな感じがする……。</Dialog>
        </Dialogs>
      </SDL2>
    </Entry>
    <Entry Unknown0="2541825224" Unknown1="2525695243">
      <SDL2 Key="502122316">
        <Unknown>
          <Entry>
            <Values>
              <Entry>
                <Value0>19443</Value0>
                <Value1>0</Value1>
              </Entry>
            </Values>
            <Value0>147456</Value0>
            <Value1>65536</Value1>
          </Entry>
        </Unknown>
        <Dialogs>
          <Dialog>高嶺</Dialog>
          <Dialog>卵の入ってないプリンって、それはもうゼリーだと思う。</Dialog>
        </Dialogs>
      </SDL2>
    </Entry>
    <Entry Unknown0="3466545951" Unknown1="3043386409">
      <SDL2 Key="502122316">
        <Unknown>
          <Entry>
            <Values>
              <Entry>
                <Value0>19444</Value0>
                <Value1>0</Value1>
              </Entry>
            </Values>
            <Value0>147456</Value0>
            <Value1>65536</Value1>
          </Entry>
        </Unknown>
        <Dialogs>
          <Dialog>高嶺</Dialog>
          <Dialog>墾田永年私財法。</Dialog>
        </Dialogs>
      </SDL2>
    </Entry>
    <Entry Unknown0="3967423037" Unknown1="3988619780">
      <SDL2 Key="502122316">
        <Unknown>
          <Entry>
            <Values>
              <Entry>
                <Value0>19445</Value0>
                <Value1>0</Value1>
              </Entry>
            </Values>
            <Value0>147456</Value0>
            <Value1>65536</Value1>
          </Entry>
        </Unknown>
        <Dialogs>
          <Dialog>高嶺</Dialog>
          <Dialog>必殺、ノイズキャンセラーキャンセラー！</Dialog>
        </Dialogs>
      </SDL2>
    </Entry>
    <Entry Unknown0="3352427544" Unknown1="1172004187">
      <SDL2 Key="3317586467">
        <Unknown>
          <Entry>
            <Values>
              <Entry>
                <Value0>19446</Value0>
                <Value1>0</Value1>
              </Entry>
            </Values>
            <Value0>147456</Value0>
            <Value1>65536</Value1>
          </Entry>
        </Unknown>
        <Dialogs>
          <Dialog>高嶺</Dialog>
          <Dialog>うちは蕎麦屋じゃないよ！</Dialog>
        </Dialogs>
      </SDL2>
    </Entry>
    <Entry Unknown0="1055857519" Unknown1="1622586489">
      <SDL2 Key="3317586467">
        <Unknown>
          <Entry>
            <Values>
              <Entry>
                <Value0>19447</Value0>
                <Value1>0</Value1>
              </Entry>
            </Values>
            <Value0>147456</Value0>
            <Value1>65536</Value1>
          </Entry>
        </Unknown>
        <Dialogs>
          <Dialog>高嶺</Dialog>
          <Dialog>お探しのページは見つかりませんでした。</Dialog>
        </Dialogs>
      </SDL2>
    </Entry>
    <Entry Unknown0="1556783757" Unknown1="1510855252">
      <SDL2 Key="3317586467">
        <Unknown>
          <Entry>
            <Values>
              <Entry>
                <Value0>19448</Value0>
                <Value1>0</Value1>
              </Entry>
            </Values>
            <Value0>147456</Value0>
            <Value1>65536</Value1>
          </Entry>
        </Unknown>
        <Dialogs>
          <Dialog>高嶺</Dialog>
          <Dialog>へい、らっしゃい！</Dialog>
        </Dialogs>
      </SDL2>
    </Entry>
    <Entry Unknown0="924945512" Unknown1="808168875">
      <SDL2 Key="3317586467">
        <Unknown>
          <Entry>
            <Values>
              <Entry>
                <Value0>19449</Value0>
                <Value1>0</Value1>
              </Entry>
            </Values>
            <Value0>147456</Value0>
            <Value1>65536</Value1>
          </Entry>
        </Unknown>
        <Dialogs>
          <Dialog>高嶺</Dialog>
          <Dialog>お母さ……先生！</Dialog>
        </Dialogs>
      </SDL2>
    </Entry>
    <Entry Unknown0="1849666495" Unknown1="3540387017">
      <SDL2 Key="3317586467">
        <Unknown>
          <Entry>
            <Values>
              <Entry>
                <Value0>19450</Value0>
                <Value1>0</Value1>
              </Entry>
            </Values>
            <Value0>147456</Value0>
            <Value1>65536</Value1>
          </Entry>
        </Unknown>
        <Dialogs>
          <Dialog>高嶺</Dialog>
          <Dialog>アノリフィカビリチュディニタティバス。</Dialog>
        </Dialogs>
      </SDL2>
    </Entry>
    <Entry Unknown0="2350543581" Unknown1="123544228">
      <SDL2 Key="3891163517">
        <Unknown>
          <Entry>
            <Values>
              <Entry>
                <Value0>19451</Value0>
                <Value1>0</Value1>
              </Entry>
            </Values>
            <Value0>147456</Value0>
            <Value1>65536</Value1>
          </Entry>
        </Unknown>
        <Dialogs>
          <Dialog>高嶺</Dialog>
          <Dialog>じゅげむじゅげむ。</Dialog>
        </Dialogs>
      </SDL2>
    </Entry>
    <Entry Unknown0="1735482552" Unknown1="4017880571">
      <SDL2 Key="3891163517">
        <Unknown>
          <Entry>
            <Values>
              <Entry>
                <Value0>19452</Value0>
                <Value1>0</Value1>
              </Entry>
            </Values>
            <Value0>147456</Value0>
            <Value1>65536</Value1>
          </Entry>
        </Unknown>
        <Dialogs>
          <Dialog>高嶺</Dialog>
          <Dialog>リャマとアルパカどっちが大事なの!?</Dialog>
        </Dialogs>
      </SDL2>
    </Entry>
    <Entry Unknown0="3733945103" Unknown1="2388022297">
      <SDL2 Key="3891163517">
        <Unknown>
          <Entry>
            <Values>
              <Entry>
                <Value0>19453</Value0>
                <Value1>0</Value1>
              </Entry>
            </Values>
            <Value0>147456</Value0>
            <Value1>65536</Value1>
          </Entry>
        </Unknown>
        <Dialogs>
          <Dialog>高嶺</Dialog>
          <Dialog>そう……ハシビロコウなのね……。</Dialog>
        </Dialogs>
      </SDL2>
    </Entry>
    <Entry Unknown0="4234805805" Unknown1="4105007860">
      <SDL2 Key="3891163517">
        <Unknown>
          <Entry>
            <Values>
              <Entry>
                <Value0>19454</Value0>
                <Value1>0</Value1>
              </Entry>
            </Values>
            <Value0>147456</Value0>
            <Value1>65536</Value1>
          </Entry>
        </Unknown>
        <Dialogs>
          <Dialog>高嶺</Dialog>
          <Dialog>とっぴんぱらりのぷう。</Dialog>
        </Dialogs>
      </SDL2>
    </Entry>
    <Entry Unknown0="3619810312" Unknown1="1523273035">
      <SDL2 Key="3891163517">
        <Unknown>
          <Entry>
            <Values>
              <Entry>
                <Value0>19455</Value0>
                <Value1>0</Value1>
              </Entry>
            </Values>
            <Value0>147456</Value0>
            <Value1>65536</Value1>
          </Entry>
        </Unknown>
        <Dialogs>
          <Dialog>高嶺</Dialog>
          <Dialog>めがねめがね……。</Dialog>
        </Dialogs>
      </SDL2>
    </Entry>
    <Entry Unknown0="249498463" Unknown1="2040964201">
      <SDL2 Key="3891163517">
        <Unknown>
          <Entry>
            <Values>
              <Entry>
                <Value0>19456</Value0>
                <Value1>0</Value1>
              </Entry>
            </Values>
            <Value0>147456</Value0>
            <Value1>65536</Value1>
          </Entry>
        </Unknown>
        <Dialogs>
          <Dialog>高嶺</Dialog>
          <Dialog>規制退場にご協力ください。</Dialog>
        </Dialogs>
      </SDL2>
    </Entry>
    <Entry Unknown0="750441085" Unknown1="2717762116">
      <SDL2 Key="2914120788">
        <Unknown>
          <Entry>
            <Values>
              <Entry>
                <Value0>19457</Value0>
                <Value1>0</Value1>
              </Entry>
            </Values>
            <Value0>147456</Value0>
            <Value1>65536</Value1>
          </Entry>
          <Entry>
            <Values>
              <Entry>
                <Value0>19458</Value0>
                <Value1>0</Value1>
              </Entry>
            </Values>
            <Value0>147456</Value0>
            <Value1>65536</Value1>
          </Entry>
        </Unknown>
        <Dialogs>
          <Dialog>高嶺</Dialog>
          <Dialog>そうだ、とわのへ行こう。</Dialog>
        </Dialogs>
      </SDL2>
    </Entry>
    <Entry Unknown0="118602840" Unknown1="152804763">
      <SDL2 Key="2914120788">
        <Unknown>
          <Entry>
            <Values>
              <Entry>
                <Value0>19459</Value0>
                <Value1>0</Value1>
              </Entry>
            </Values>
            <Value0>147456</Value0>
            <Value1>65536</Value1>
          </Entry>
        </Unknown>
        <Dialogs>
          <Dialog>高嶺</Dialog>
          <Dialog>やった！　帰宅部が全国大会進出したよ！</Dialog>
        </Dialogs>
      </SDL2>
    </Entry>
    <Entry Unknown0="2117065647" Unknown1="351728825">
      <SDL2 Key="2914120788">
        <Unknown>
          <Entry>
            <Values>
              <Entry>
                <Value0>19460</Value0>
                <Value1>0</Value1>
              </Entry>
            </Values>
            <Value0>147456</Value0>
            <Value1>65536</Value1>
          </Entry>
        </Unknown>
        <Dialogs>
          <Dialog>高嶺</Dialog>
          <Dialog>それ脇差だから、忍者刀じゃないから。</Dialog>
        </Dialogs>
      </SDL2>
    </Entry>
    <Entry Unknown0="2617926349" Unknown1="776802964">
      <SDL2 Key="2914120788">
        <Unknown>
          <Entry>
            <Values>
              <Entry>
                <Value0>19461</Value0>
                <Value1>0</Value1>
              </Entry>
            </Values>
            <Value0>147456</Value0>
            <Value1>65536</Value1>
          </Entry>
        </Unknown>
        <Dialogs>
          <Dialog>高嶺</Dialog>
          <Dialog>パスワードが違います。</Dialog>
        </Dialogs>
      </SDL2>
    </Entry>
    <Entry Unknown0="2002865320" Unknown1="3295407595">
      <SDL2 Key="2914120788">
        <Unknown>
          <Entry>
            <Values>
              <Entry>
                <Value0>19462</Value0>
                <Value1>0</Value1>
              </Entry>
            </Values>
            <Value0>147456</Value0>
            <Value1>65536</Value1>
          </Entry>
        </Unknown>
        <Dialogs>
          <Dialog>高嶺</Dialog>
          <Dialog>かしわ、さくら、もみじ、ぼたん。</Dialog>
        </Dialogs>
      </SDL2>
    </Entry>
    <Entry Unknown0="2927586303" Unknown1="2806400009">
      <SDL2 Key="2914120788">
        <Unknown>
          <Entry>
            <Values>
              <Entry>
                <Value0>19463</Value0>
                <Value1>0</Value1>
              </Entry>
            </Values>
            <Value0>147456</Value0>
            <Value1>65536</Value1>
          </Entry>
        </Unknown>
        <Dialogs>
          <Dialog>高嶺</Dialog>
          <Dialog>またコードが絡まってる……ブロークンウィンドウね。</Dialog>
        </Dialogs>
      </SDL2>
    </Entry>
    <Entry Unknown0="3428463133" Unknown1="4221395684">
      <SDL2 Key="3756993199">
        <Unknown>
          <Entry>
            <Values>
              <Entry>
                <Value0>19464</Value0>
                <Value1>0</Value1>
              </Entry>
            </Values>
            <Value0>147456</Value0>
            <Value1>65536</Value1>
          </Entry>
        </Unknown>
        <Dialogs>
          <Dialog>高嶺</Dialog>
          <Dialog>石橋を叩いて割る。</Dialog>
        </Dialogs>
      </SDL2>
    </Entry>
    <Entry Unknown0="2813402360" Unknown1="2478521659">
      <SDL2 Key="3756993199">
        <Unknown>
          <Entry>
            <Values>
              <Entry>
                <Value0>19465</Value0>
                <Value1>0</Value1>
              </Entry>
            </Values>
            <Value0>147456</Value0>
            <Value1>65536</Value1>
          </Entry>
        </Unknown>
        <Dialogs>
          <Dialog>高嶺</Dialog>
          <Dialog>待てばカイロのヒエログリフ。</Dialog>
        </Dialogs>
      </SDL2>
    </Entry>
    <Entry Unknown0="516897615" Unknown1="1922471001">
      <SDL2 Key="3756993199">
        <Unknown>
          <Entry>
            <Values>
              <Entry>
                <Value0>19466</Value0>
                <Value1>0</Value1>
              </Entry>
            </Values>
            <Value0>147456</Value0>
            <Value1>65536</Value1>
          </Entry>
        </Unknown>
        <Dialogs>
          <Dialog>高嶺</Dialog>
          <Dialog>深爪しちゃった……。</Dialog>
        </Dialogs>
      </SDL2>
    </Entry>
    <Entry Unknown0="1017823853" Unknown1="2297279028">
      <SDL2 Key="3756993199">
        <Unknown>
          <Entry>
            <Values>
              <Entry>
                <Value0>19467</Value0>
                <Value1>0</Value1>
              </Entry>
            </Values>
            <Value0>147456</Value0>
            <Value1>65536</Value1>
          </Entry>
        </Unknown>
        <Dialogs>
          <Dialog>高嶺</Dialog>
          <Dialog>武器や防具は装備しないと意味がありませんよ。</Dialog>
        </Dialogs>
      </SDL2>
    </Entry>
    <Entry Unknown0="385985608" Unknown1="772509067">
      <SDL2 Key="4282339834">
        <Unknown>
          <Entry>
            <Values>
              <Entry>
                <Value0>19468</Value0>
                <Value1>0</Value1>
              </Entry>
            </Values>
            <Value0>147456</Value0>
            <Value1>65536</Value1>
          </Entry>
        </Unknown>
        <Dialogs>
          <Dialog>高嶺</Dialog>
          <Dialog>明日は明日の風が「ドーーーーン！」</Dialog>
        </Dialogs>
      </SDL2>
    </Entry>
    <Entry Unknown0="1310706591" Unknown1="233235625">
      <SDL2 Key="4282339834">
        <Unknown>
          <Entry>
            <Values>
              <Entry>
                <Value0>19469</Value0>
                <Value1>0</Value1>
              </Entry>
            </Values>
            <Value0>147456</Value0>
            <Value1>65536</Value1>
          </Entry>
        </Unknown>
        <Dialogs>
          <Dialog>高嶺</Dialog>
          <Dialog>論より「ドーーーーン！」</Dialog>
        </Dialogs>
      </SDL2>
    </Entry>
    <Entry Unknown0="1828360893" Unknown1="1430061700">
      <SDL2 Key="4282339834">
        <Unknown>
          <Entry>
            <Values>
              <Entry>
                <Value0>19470</Value0>
                <Value1>0</Value1>
              </Entry>
            </Values>
            <Value0>147456</Value0>
            <Value1>65536</Value1>
          </Entry>
        </Unknown>
        <Dialogs>
          <Dialog>高嶺</Dialog>
          <Dialog>猿も木から「ドーーーーン！」</Dialog>
        </Dialogs>
      </SDL2>
    </Entry>
    <Entry Unknown0="1196522648" Unknown1="4250656219">
      <SDL2 Key="4282339834">
        <Unknown>
          <Entry>
            <Values>
              <Entry>
                <Value0>19471</Value0>
                <Value1>0</Value1>
              </Entry>
            </Values>
            <Value0>147456</Value0>
            <Value1>65536</Value1>
          </Entry>
        </Unknown>
        <Dialogs>
          <Dialog>高嶺</Dialog>
          <Dialog>今日の降水確率は１２０％。いつもより余計に降っております！</Dialog>
        </Dialogs>
      </SDL2>
    </Entry>
    <Entry Unknown0="3194985455" Unknown1="3627431161">
      <SDL2 Key="3085092049">
        <Unknown>
          <Entry>
            <Values>
              <Entry>
                <Value0>19472</Value0>
                <Value1>0</Value1>
              </Entry>
            </Values>
            <Value0>147456</Value0>
            <Value1>65536</Value1>
          </Entry>
        </Unknown>
        <Dialogs>
          <Dialog>高嶺</Dialog>
          <Dialog>今日のことわざは……二階からぼた餅！</Dialog>
        </Dialogs>
      </SDL2>
    </Entry>
    <Entry Unknown0="3695845901" Unknown1="3800912596">
      <SDL2 Key="3085092049">
        <Unknown>
          <Entry>
            <Values>
              <Entry>
                <Value0>19473</Value0>
                <Value1>0</Value1>
              </Entry>
            </Values>
            <Value0>147456</Value0>
            <Value1>65536</Value1>
          </Entry>
        </Unknown>
        <Dialogs>
          <Dialog>高嶺</Dialog>
          <Dialog>苺のモンブランって美味しそうじゃない？</Dialog>
        </Dialogs>
      </SDL2>
    </Entry>
    <Entry Unknown0="3080785128" Unknown1="2292919595">
      <SDL2 Key="3085092049">
        <Unknown>
          <Entry>
            <Values>
              <Entry>
                <Value0>19474</Value0>
                <Value1>0</Value1>
              </Entry>
            </Values>
            <Value0>147456</Value0>
            <Value1>65536</Value1>
          </Entry>
        </Unknown>
        <Dialogs>
          <Dialog>高嶺</Dialog>
          <Dialog>むかーしむかし、あるところに、おじいさんとおばあさんとオッス、マナカだよ♪</Dialog>
        </Dialogs>
      </SDL2>
    </Entry>
    <Entry Unknown0="4005505855" Unknown1="1803977801">
      <SDL2 Key="3085092049">
        <Unknown>
          <Entry>
            <Values>
              <Entry>
                <Value0>19475</Value0>
                <Value1>0</Value1>
              </Entry>
            </Values>
            <Value0>147456</Value0>
            <Value1>65536</Value1>
          </Entry>
        </Unknown>
        <Dialogs>
          <Dialog>高嶺</Dialog>
          <Dialog>それはそれは、甘ーい甘ーいイカの塩辛。</Dialog>
        </Dialogs>
      </SDL2>
    </Entry>
    <Entry Unknown0="211481181" Unknown1="2950537764">
      <SDL2 Key="3085092049">
        <Unknown>
          <Entry>
            <Values>
              <Entry>
                <Value0>19476</Value0>
                <Value1>0</Value1>
              </Entry>
            </Values>
            <Value0>147456</Value0>
            <Value1>65536</Value1>
          </Entry>
        </Unknown>
        <Dialogs>
          <Dialog>高嶺</Dialog>
          <Dialog>願いを一つだけかなえてくれる、魔法の……土瓶♪</Dialog>
        </Dialogs>
      </SDL2>
    </Entry>
    <Entry Unknown0="3891387448" Unknown1="1207663995">
      <SDL2 Key="3085092049">
        <Unknown>
          <Entry>
            <Values>
              <Entry>
                <Value0>19477</Value0>
                <Value1>0</Value1>
              </Entry>
            </Values>
            <Value0>147456</Value0>
            <Value1>65536</Value1>
          </Entry>
        </Unknown>
        <Dialogs>
          <Dialog>高嶺</Dialog>
          <Dialog>まなか、まんなか、まままなか！</Dialog>
        </Dialogs>
      </SDL2>
    </Entry>
    <Entry Unknown0="1578105743" Unknown1="651613337">
      <SDL2 Key="3643996988">
        <Unknown>
          <Entry>
            <Values>
              <Entry>
                <Value0>19478</Value0>
                <Value1>0</Value1>
              </Entry>
            </Values>
            <Value0>147456</Value0>
            <Value1>65536</Value1>
          </Entry>
        </Unknown>
        <Dialogs>
          <Dialog>高嶺</Dialog>
          <Dialog>ピッチャー投げたー！　打ったー！　走ったー！　そして、飛んだー！</Dialog>
        </Dialogs>
      </SDL2>
    </Entry>
    <Entry Unknown0="2095743661" Unknown1="1546515060">
      <SDL2 Key="3643996988">
        <Unknown>
          <Entry>
            <Values>
              <Entry>
                <Value0>19479</Value0>
                <Value1>0</Value1>
              </Entry>
            </Values>
            <Value0>147456</Value0>
            <Value1>65536</Value1>
          </Entry>
        </Unknown>
        <Dialogs>
          <Dialog>高嶺</Dialog>
          <Dialog>ボンジュール花火♪</Dialog>
        </Dialogs>
      </SDL2>
    </Entry>
    <Entry Unknown0="1463905416" Unknown1="4065054155">
      <SDL2 Key="3643996988">
        <Unknown>
          <Entry>
            <Values>
              <Entry>
                <Value0>19480</Value0>
                <Value1>0</Value1>
              </Entry>
            </Values>
            <Value0>147456</Value0>
            <Value1>65536</Value1>
          </Entry>
        </Unknown>
        <Dialogs>
          <Dialog>高嶺</Dialog>
          <Dialog>作った肉じゃが余っちゃって……。</Dialog>
        </Dialogs>
      </SDL2>
    </Entry>
    <Entry Unknown0="2388626399" Unknown1="3508937961">
      <SDL2 Key="3643996988">
        <Unknown>
          <Entry>
            <Values>
              <Entry>
                <Value0>19481</Value0>
                <Value1>0</Value1>
              </Entry>
            </Values>
            <Value0>147456</Value0>
            <Value1>65536</Value1>
          </Entry>
        </Unknown>
        <Dialogs>
          <Dialog>高嶺</Dialog>
          <Dialog>よしきた、高嶺づかみ……！</Dialog>
        </Dialogs>
      </SDL2>
    </Entry>
    <Entry Unknown0="2889503485" Unknown1="159204036">
      <SDL2 Key="3643996988">
        <Unknown>
          <Entry>
            <Values>
              <Entry>
                <Value0>19482</Value0>
                <Value1>0</Value1>
              </Entry>
            </Values>
            <Value0>147456</Value0>
            <Value1>65536</Value1>
          </Entry>
        </Unknown>
        <Dialogs>
          <Dialog>高嶺</Dialog>
          <Dialog>かき氷のシロップ余らせちゃうから、大量に使うレシピを考えてみたの。……食べて？</Dialog>
        </Dialogs>
      </SDL2>
    </Entry>
    <Entry Unknown0="2274442456" Unknown1="2711297307">
      <SDL2 Key="3643996988">
        <Unknown>
          <Entry>
            <Values>
              <Entry>
                <Value0>19483</Value0>
                <Value1>0</Value1>
              </Entry>
            </Values>
            <Value0>147456</Value0>
            <Value1>65536</Value1>
          </Entry>
        </Unknown>
        <Dialogs>
          <Dialog>高嶺</Dialog>
          <Dialog>ご飯にする？　お風呂にする？　それとも……あ・た・み？</Dialog>
        </Dialogs>
      </SDL2>
    </Entry>
    <Entry Unknown0="4272905007" Unknown1="2356573241">
      <SDL2 Key="3643996988">
        <Unknown>
          <Entry>
            <Values>
              <Entry>
                <Value0>19484</Value0>
                <Value1>0</Value1>
              </Entry>
            </Values>
            <Value0>147456</Value0>
            <Value1>65536</Value1>
          </Entry>
        </Unknown>
        <Dialogs>
          <Dialog>高嶺</Dialog>
          <Dialog>冷やしシャンプーはじめました。</Dialog>
        </Dialogs>
      </SDL2>
    </Entry>
    <Entry Unknown0="478863949" Unknown1="3066925588">
      <SDL2 Key="2682486291">
        <Unknown>
          <Entry>
            <Values>
              <Entry>
                <Value0>19485</Value0>
                <Value1>0</Value1>
              </Entry>
            </Values>
            <Value0>147456</Value0>
            <Value1>65536</Value1>
          </Entry>
        </Unknown>
        <Dialogs>
          <Dialog>高嶺</Dialog>
          <Dialog>メガテリヤキうどんバーガーセット８つですね。店内でお召し上がりですか？</Dialog>
        </Dialogs>
      </SDL2>
    </Entry>
    <Entry Unknown0="4158770216" Unknown1="1558932843">
      <SDL2 Key="2682486291">
        <Unknown>
          <Entry>
            <Values>
              <Entry>
                <Value0>19486</Value0>
                <Value1>0</Value1>
              </Entry>
            </Values>
            <Value0>147456</Value0>
            <Value1>65536</Value1>
          </Entry>
        </Unknown>
        <Dialogs>
          <Dialog>高嶺</Dialog>
          <Dialog>箸先３cm以上は汚しちゃだめ！</Dialog>
        </Dialogs>
      </SDL2>
    </Entry>
    <Entry Unknown0="788523903" Unknown1="1069991049">
      <SDL2 Key="2682486291">
        <Unknown>
          <Entry>
            <Values>
              <Entry>
                <Value0>19487</Value0>
                <Value1>0</Value1>
              </Entry>
            </Values>
            <Value0>147456</Value0>
            <Value1>65536</Value1>
          </Entry>
        </Unknown>
        <Dialogs>
          <Dialog>高嶺</Dialog>
          <Dialog>すごい！　渡し込み！</Dialog>
        </Dialogs>
      </SDL2>
    </Entry>
    <Entry Unknown0="1289400989" Unknown1="1662902884">
      <SDL2 Key="2682486291">
        <Unknown>
          <Entry>
            <Values>
              <Entry>
                <Value0>19488</Value0>
                <Value1>0</Value1>
              </Entry>
            </Values>
            <Value0>147456</Value0>
            <Value1>65536</Value1>
          </Entry>
        </Unknown>
        <Dialogs>
          <Dialog>高嶺</Dialog>
          <Dialog>灰色の脳細胞なんて、信用できない……。</Dialog>
        </Dialogs>
      </SDL2>
    </Entry>
    <Entry Unknown0="657562744" Unknown1="188464571">
      <SDL2 Key="2682486291">
        <Unknown>
          <Entry>
            <Values>
              <Entry>
                <Value0>19489</Value0>
                <Value1>0</Value1>
              </Entry>
            </Values>
            <Value0>147456</Value0>
            <Value1>65536</Value1>
          </Entry>
        </Unknown>
        <Dialogs>
          <Dialog>高嶺</Dialog>
          <Dialog>今日のわたしのラッキースターは物干し。</Dialog>
        </Dialogs>
      </SDL2>
    </Entry>
    <Entry Unknown0="2656025551" Unknown1="3927315673">
      <SDL2 Key="2682486291">
        <Unknown>
          <Entry>
            <Values>
              <Entry>
                <Value0>19490</Value0>
                <Value1>0</Value1>
              </Entry>
            </Values>
            <Value0>147456</Value0>
            <Value1>65536</Value1>
          </Entry>
        </Unknown>
        <Dialogs>
          <Dialog>高嶺</Dialog>
          <Dialog>ではさっきのオッスはお蔵入りということで……。</Dialog>
        </Dialogs>
      </SDL2>
    </Entry>
    <Entry Unknown0="3156886253" Unknown1="275591860">
      <SDL2 Key="3241387373">
        <Unknown>
          <Entry>
            <Values>
              <Entry>
                <Value0>19491</Value0>
                <Value1>0</Value1>
              </Entry>
            </Values>
            <Value0>147456</Value0>
            <Value1>65536</Value1>
          </Entry>
        </Unknown>
        <Dialogs>
          <Dialog>高嶺</Dialog>
          <Dialog>いいもん、南米でならわかってもらえるもん！</Dialog>
        </Dialogs>
      </SDL2>
    </Entry>
    <Entry Unknown0="2541825224" Unknown1="1183517963">
      <SDL2 Key="3241387373">
        <Unknown>
          <Entry>
            <Values>
              <Entry>
                <Value0>19492</Value0>
                <Value1>0</Value1>
              </Entry>
            </Values>
            <Value0>147456</Value0>
            <Value1>65536</Value1>
          </Entry>
        </Unknown>
        <Dialogs>
          <Dialog>高嶺</Dialog>
          <Dialog>つむじっ！</Dialog>
        </Dialogs>
      </SDL2>
    </Entry>
    <Entry Unknown0="3466545951" Unknown1="1701209129">
      <SDL2 Key="3241387373">
        <Unknown>
          <Entry>
            <Values>
              <Entry>
                <Value0>19493</Value0>
                <Value1>0</Value1>
              </Entry>
            </Values>
            <Value0>147456</Value0>
            <Value1>65536</Value1>
          </Entry>
        </Unknown>
        <Dialogs>
          <Dialog>高嶺</Dialog>
          <Dialog>ここに金柑お願いします。</Dialog>
        </Dialogs>
      </SDL2>
    </Entry>
    <Entry Unknown0="3967423037" Unknown1="1035829764">
      <SDL2 Key="3241387373">
        <Unknown>
          <Entry>
            <Values>
              <Entry>
                <Value0>19494</Value0>
                <Value1>0</Value1>
              </Entry>
            </Values>
            <Value0>147456</Value0>
            <Value1>65536</Value1>
          </Entry>
        </Unknown>
        <Dialogs>
          <Dialog>高嶺</Dialog>
          <Dialog>突然ですが、実家に帰らせていただきます。</Dialog>
        </Dialogs>
      </SDL2>
    </Entry>
    <Entry Unknown0="3352427544" Unknown1="2514181467">
      <SDL2 Key="3241387373">
        <Unknown>
          <Entry>
            <Values>
              <Entry>
                <Value0>19495</Value0>
                <Value1>0</Value1>
              </Entry>
            </Values>
            <Value0>147456</Value0>
            <Value1>65536</Value1>
          </Entry>
        </Unknown>
        <Dialogs>
          <Dialog>高嶺</Dialog>
          <Dialog>一瞬の輝きに賭けたいの！</Dialog>
        </Dialogs>
      </SDL2>
    </Entry>
    <Entry Unknown0="1055857519" Unknown1="2964763769">
      <SDL2 Key="3241387373">
        <Unknown>
          <Entry>
            <Values>
              <Entry>
                <Value0>19496</Value0>
                <Value1>0</Value1>
              </Entry>
            </Values>
            <Value0>147456</Value0>
            <Value1>65536</Value1>
          </Entry>
        </Unknown>
        <Dialogs>
          <Dialog>高嶺</Dialog>
          <Dialog>NULL文字入ってる？</Dialog>
        </Dialogs>
      </SDL2>
    </Entry>
    <Entry Unknown0="1556783757" Unknown1="2316161620">
      <SDL2 Key="3241387373">
        <Unknown>
          <Entry>
            <Values>
              <Entry>
                <Value0>19497</Value0>
                <Value1>0</Value1>
              </Entry>
            </Values>
            <Value0>147456</Value0>
            <Value1>65536</Value1>
          </Entry>
        </Unknown>
        <Dialogs>
          <Dialog>高嶺</Dialog>
          <Dialog>趣味はお紅茶、特技はおテニスを少々。</Dialog>
        </Dialogs>
      </SDL2>
    </Entry>
    <Entry Unknown0="924945512" Unknown1="3760958891">
      <SDL2 Key="3781417929">
        <Unknown>
          <Entry>
            <Values>
              <Entry>
                <Value0>19498</Value0>
                <Value1>0</Value1>
              </Entry>
            </Values>
            <Value0>147456</Value0>
            <Value1>65536</Value1>
          </Entry>
        </Unknown>
        <Dialogs>
          <Dialog>高嶺</Dialog>
          <Dialog>鮭スピア？　あ、そういうことか。</Dialog>
        </Dialogs>
      </SDL2>
    </Entry>
    <Entry Unknown0="1849666495" Unknown1="50726089">
      <SDL2 Key="3781417929">
        <Unknown>
          <Entry>
            <Values>
              <Entry>
                <Value0>19499</Value0>
                <Value1>0</Value1>
              </Entry>
            </Values>
            <Value0>147456</Value0>
            <Value1>65536</Value1>
          </Entry>
        </Unknown>
        <Dialogs>
          <Dialog>高嶺</Dialog>
          <Dialog>薔薇なの？　檸檬なの？　どっちにしろ難しくて書けないよ……。</Dialog>
        </Dialogs>
      </SDL2>
    </Entry>
    <Entry Unknown0="2350543581" Unknown1="3613205156">
      <SDL2 Key="3781417929">
        <Unknown>
          <Entry>
            <Values>
              <Entry>
                <Value0>19500</Value0>
                <Value1>0</Value1>
              </Entry>
            </Values>
            <Value0>147456</Value0>
            <Value1>65536</Value1>
          </Entry>
        </Unknown>
        <Dialogs>
          <Dialog>高嶺</Dialog>
          <Dialog>人の名前にしては、濁点が多すぎるよ……。</Dialog>
        </Dialogs>
      </SDL2>
    </Entry>
    <Entry Unknown0="1735482552" Unknown1="1065090555">
      <SDL2 Key="3781417929">
        <Unknown>
          <Entry>
            <Values>
              <Entry>
                <Value0>19501</Value0>
                <Value1>0</Value1>
              </Entry>
            </Values>
            <Value0>147456</Value0>
            <Value1>65536</Value1>
          </Entry>
        </Unknown>
        <Dialogs>
          <Dialog>高嶺</Dialog>
          <Dialog>洗濯機の中で泳ぎたいな……。</Dialog>
        </Dialogs>
      </SDL2>
    </Entry>
    <Entry Unknown0="3733945103" Unknown1="1582715929">
      <SDL2 Key="3781417929">
        <Unknown>
          <Entry>
            <Values>
              <Entry>
                <Value0>19502</Value0>
                <Value1>0</Value1>
              </Entry>
            </Values>
            <Value0>147456</Value0>
            <Value1>65536</Value1>
          </Entry>
        </Unknown>
        <Dialogs>
          <Dialog>高嶺</Dialog>
          <Dialog>綿棒くらいなら大丈夫！　ラケットの代わりになるから。</Dialog>
        </Dialogs>
      </SDL2>
    </Entry>
    <Entry Unknown0="4234805805" Unknown1="615346932">
      <SDL2 Key="3781417929">
        <Unknown>
          <Entry>
            <Values>
              <Entry>
                <Value0>19503</Value0>
                <Value1>0</Value1>
              </Entry>
            </Values>
            <Value0>147456</Value0>
            <Value1>65536</Value1>
          </Entry>
        </Unknown>
        <Dialogs>
          <Dialog>高嶺</Dialog>
          <Dialog>ごめんね、やっぱり加湿器に香水入れちゃダメだった……。</Dialog>
        </Dialogs>
      </SDL2>
    </Entry>
    <Entry Unknown0="3619810312" Unknown1="2328579403">
      <SDL2 Key="2838781599">
        <Unknown>
          <Entry>
            <Values>
              <Entry>
                <Value0>19504</Value0>
                <Value1>0</Value1>
              </Entry>
            </Values>
            <Value0>147456</Value0>
            <Value1>65536</Value1>
          </Entry>
        </Unknown>
        <Dialogs>
          <Dialog>高嶺</Dialog>
          <Dialog>オッス、博多だよ♪　……テヘ▼</Dialog>
        </Dialogs>
      </SDL2>
    </Entry>
    <Entry Unknown0="249498463" Unknown1="2846270569">
      <SDL2 Key="2838781599">
        <Unknown>
          <Entry>
            <Values>
              <Entry>
                <Value0>19505</Value0>
                <Value1>0</Value1>
              </Entry>
            </Values>
            <Value0>147456</Value0>
            <Value1>65536</Value1>
          </Entry>
        </Unknown>
        <Dialogs>
          <Dialog>高嶺</Dialog>
          <Dialog>オッス、曼荼羅だよ♪　……テヘ▼</Dialog>
        </Dialogs>
      </SDL2>
    </Entry>
    <Entry Unknown0="750441085" Unknown1="1912455748">
      <SDL2 Key="2838781599">
        <Unknown>
          <Entry>
            <Values>
              <Entry>
                <Value0>19506</Value0>
                <Value1>0</Value1>
              </Entry>
            </Values>
            <Value0>147456</Value0>
            <Value1>65536</Value1>
          </Entry>
        </Unknown>
        <Dialogs>
          <Dialog>高嶺</Dialog>
          <Dialog>オッス、田中だよ♪　……テヘ▼</Dialog>
        </Dialogs>
      </SDL2>
    </Entry>
    <Entry Unknown0="118602840" Unknown1="3642465691">
      <SDL2 Key="2838781599">
        <Unknown>
          <Entry>
            <Values>
              <Entry>
                <Value0>19507</Value0>
                <Value1>0</Value1>
              </Entry>
            </Values>
            <Value0>147456</Value0>
            <Value1>65536</Value1>
          </Entry>
        </Unknown>
        <Dialogs>
          <Dialog>高嶺</Dialog>
          <Dialog>オッス、仲間だよ♪　……テヘ▼</Dialog>
        </Dialogs>
      </SDL2>
    </Entry>
    <Entry Unknown0="2117065647" Unknown1="3841389753">
      <SDL2 Key="2838781599">
        <Unknown>
          <Entry>
            <Values>
              <Entry>
                <Value0>19508</Value0>
                <Value1>0</Value1>
              </Entry>
            </Values>
            <Value0>147456</Value0>
            <Value1>65536</Value1>
          </Entry>
        </Unknown>
        <Dialogs>
          <Dialog>高嶺</Dialog>
          <Dialog>オッス、館だよ♪　……テヘ▼</Dialog>
        </Dialogs>
      </SDL2>
    </Entry>
    <Entry Unknown0="2617926349" Unknown1="3729592980">
      <SDL2 Key="2838781599">
        <Unknown>
          <Entry>
            <Values>
              <Entry>
                <Value0>19509</Value0>
                <Value1>0</Value1>
              </Entry>
            </Values>
            <Value0>147456</Value0>
            <Value1>65536</Value1>
          </Entry>
        </Unknown>
        <Dialogs>
          <Dialog>高嶺</Dialog>
          <Dialog>オッス、アロハだよ♪　……テヘ▼</Dialog>
        </Dialogs>
      </SDL2>
    </Entry>
    <Entry Unknown0="2002865320" Unknown1="879488491">
      <SDL2 Key="3647243754">
        <Unknown>
          <Entry>
            <Values>
              <Entry>
                <Value0>19510</Value0>
                <Value1>0</Value1>
              </Entry>
            </Values>
            <Value0>147456</Value0>
            <Value1>65536</Value1>
          </Entry>
        </Unknown>
        <Dialogs>
          <Dialog>高嶺</Dialog>
          <Dialog>オッス……オッス♪　……テヘ▼</Dialog>
        </Dialogs>
      </SDL2>
    </Entry>
    <Entry Unknown0="2927586303" Unknown1="1464222729">
      <SDL2 Key="3647243754">
        <Unknown>
          <Entry>
            <Values>
              <Entry>
                <Value0>19511</Value0>
                <Value1>0</Value1>
              </Entry>
            </Values>
            <Value0>147456</Value0>
            <Value1>65536</Value1>
          </Entry>
        </Unknown>
        <Dialogs>
          <Dialog>高嶺</Dialog>
          <Dialog>オッス、高嶺だよ♪　……テヘ▼</Dialog>
        </Dialogs>
      </SDL2>
    </Entry>
    <Entry Unknown0="3428463133" Unknown1="194863844">
      <SDL2 Key="3647243754">
        <Unknown>
          <Entry>
            <Values>
              <Entry>
                <Value0>19512</Value0>
                <Value1>0</Value1>
              </Entry>
            </Values>
            <Value0>147456</Value0>
            <Value1>65536</Value1>
          </Entry>
        </Unknown>
        <Dialogs>
          <Dialog>高嶺</Dialog>
          <Dialog>オッス、お酢だよ♪　……テヘ▼</Dialog>
        </Dialogs>
      </SDL2>
    </Entry>
    <Entry Unknown0="2813402360" Unknown1="1673215291">
      <SDL2 Key="3647243754">
        <Unknown>
          <Entry>
            <Values>
              <Entry>
                <Value0>19513</Value0>
                <Value1>0</Value1>
              </Entry>
            </Values>
            <Value0>147456</Value0>
            <Value1>65536</Value1>
          </Entry>
        </Unknown>
        <Dialogs>
          <Dialog>高嶺</Dialog>
          <Dialog>オッス、ソワソワしないで♪　……テヘ▼</Dialog>
        </Dialogs>
      </SDL2>
    </Entry>
  </Entries>
</DBIN2>